[
    {
        "CCCD": "XXXXXXXXXXXX",
        "ID": 4,
        "allergies": [
            "Không"
        ],
        "birthday": {
            "day": 15,
            "month": 12,
            "year": 1994
        },
        "bloodType": "O+",
        "chronicDiseases": [
            "Cao huyết áp"
        ],
        "email": "foo@gmail.com",
        "gender": "M",
        "insuranceID": "SVN51501291",
        "medicalRecordIDs": [],
        "name": "Rô nân đô",
        "nameFather": "Rô nân cha",
        "nameMother": "Rô nân mẹ",
        "phoneNumber": "0123456789"
    }
]